gileum/__init__.py
gileum/gileum.py
gileum/loader.py
gileum/manager.py
gileum/test.py
tests/__init__.py
tests/test_loader.py
tests/res/__init__.py
tests/res/glm_setting.py
tests/res/setting.glm.py
gileum-0.2.2.dist-info/LICENSE
gileum-0.2.2.dist-info/METADATA
gileum-0.2.2.dist-info/WHEEL
gileum-0.2.2.dist-info/top_level.txt
gileum-0.2.2.dist-info/RECORD
