Metadata-Version: 2.1
Name: gileum
Version: 0.2.2
Summary: Loader of configuration files written in Python.
Home-page: https://github.com/jjj999/gileum/
Author: Yunhyeon Jeong
Author-email: jjj999to@gmail.com
License: UNKNOWN
Platform: UNKNOWN
Requires-Python: >=3.7
Requires-Dist: pydantic
